{
  "namespaces": [
    "public"
  ],
  "name": "public",
  "tables": [
    {
      "columns": {
        "id": {
          "name": "id",
          "type": "serial",
          "unsigned": false,
          "autoincrement": true,
          "primary": true,
          "nullable": false,
          "mappedType": "integer"
        },
        "first_name": {
          "name": "first_name",
          "type": "varchar(255)",
          "unsigned": false,
          "autoincrement": false,
          "primary": false,
          "nullable": false,
          "length": 255,
          "mappedType": "string"
        },
        "last_name": {
          "name": "last_name",
          "type": "varchar(255)",
          "unsigned": false,
          "autoincrement": false,
          "primary": false,
          "nullable": false,
          "length": 255,
          "mappedType": "string"
        },
        "email": {
          "name": "email",
          "type": "varchar(255)",
          "unsigned": false,
          "autoincrement": false,
          "primary": false,
          "nullable": false,
          "length": 255,
          "mappedType": "string"
        },
        "middle_name": {
          "name": "middle_name",
          "type": "varchar(255)",
          "unsigned": false,
          "autoincrement": false,
          "primary": false,
          "nullable": true,
          "length": 255,
          "mappedType": "string"
        },
        "hashed_password": {
          "name": "hashed_password",
          "type": "text",
          "unsigned": false,
          "autoincrement": false,
          "primary": false,
          "nullable": false,
          "mappedType": "text"
        },
        "created_at": {
          "name": "created_at",
          "type": "timestamptz",
          "unsigned": false,
          "autoincrement": false,
          "primary": false,
          "nullable": false,
          "length": 6,
          "mappedType": "datetime"
        },
        "updated_at": {
          "name": "updated_at",
          "type": "timestamptz",
          "unsigned": false,
          "autoincrement": false,
          "primary": false,
          "nullable": false,
          "length": 6,
          "mappedType": "datetime"
        }
      },
      "name": "user",
      "schema": "public",
      "indexes": [
        {
          "columnNames": [
            "email"
          ],
          "composite": false,
          "keyName": "user_email_unique",
          "constraint": true,
          "primary": false,
          "unique": true
        },
        {
          "keyName": "user_pkey",
          "columnNames": [
            "id"
          ],
          "composite": false,
          "constraint": true,
          "primary": true,
          "unique": true
        }
      ],
      "checks": [],
      "foreignKeys": {},
      "nativeEnums": {}
    },
    {
      "columns": {
        "id": {
          "name": "id",
          "type": "serial",
          "unsigned": false,
          "autoincrement": true,
          "primary": true,
          "nullable": false,
          "mappedType": "integer"
        },
        "filename": {
          "name": "filename",
          "type": "varchar(255)",
          "unsigned": false,
          "autoincrement": false,
          "primary": false,
          "nullable": false,
          "length": 255,
          "mappedType": "string"
        },
        "mimetype": {
          "name": "mimetype",
          "type": "varchar(255)",
          "unsigned": false,
          "autoincrement": false,
          "primary": false,
          "nullable": false,
          "length": 255,
          "mappedType": "string"
        },
        "url": {
          "name": "url",
          "type": "varchar(255)",
          "unsigned": false,
          "autoincrement": false,
          "primary": false,
          "nullable": false,
          "length": 255,
          "mappedType": "string"
        },
        "user_id": {
          "name": "user_id",
          "type": "int",
          "unsigned": false,
          "autoincrement": false,
          "primary": false,
          "nullable": true,
          "mappedType": "integer"
        },
        "created_at": {
          "name": "created_at",
          "type": "timestamptz",
          "unsigned": false,
          "autoincrement": false,
          "primary": false,
          "nullable": false,
          "length": 6,
          "mappedType": "datetime"
        },
        "updated_at": {
          "name": "updated_at",
          "type": "timestamptz",
          "unsigned": false,
          "autoincrement": false,
          "primary": false,
          "nullable": false,
          "length": 6,
          "mappedType": "datetime"
        }
      },
      "name": "file",
      "schema": "public",
      "indexes": [
        {
          "keyName": "file_pkey",
          "columnNames": [
            "id"
          ],
          "composite": false,
          "constraint": true,
          "primary": true,
          "unique": true
        }
      ],
      "checks": [],
      "foreignKeys": {
        "file_user_id_foreign": {
          "constraintName": "file_user_id_foreign",
          "columnNames": [
            "user_id"
          ],
          "localTableName": "public.file",
          "referencedColumnNames": [
            "id"
          ],
          "referencedTableName": "public.user",
          "deleteRule": "set null",
          "updateRule": "cascade"
        }
      },
      "nativeEnums": {}
    }
  ],
  "nativeEnums": {}
}
